pptx_replace/__init__.py
pptx_replace/replace_core.py
pptx_replace/text.py
pptx_replace/utils.py
pptx_replace-0.1.6.dist-info/METADATA
pptx_replace-0.1.6.dist-info/WHEEL
pptx_replace-0.1.6.dist-info/top_level.txt
pptx_replace-0.1.6.dist-info/RECORD
