Metadata-Version: 2.1
Name: pptx-replace
Version: 0.1.6
Summary: python package for replaceing elemnets in pptx files
Author-email: John Lyu <paleneutron@outlook.com>
License: MIT
Project-URL: Source Code, https://github.com/PaleNeutron/pptx-replace
Keywords: pptx,image,replace
Requires-Python: >=3.8
Requires-Dist: python-pptx >=0.6.21
Requires-Dist: matplotlib
Requires-Dist: openpyxl >=3.0
Requires-Dist: pandas
Requires-Dist: Jinja2
Requires-Dist: numpy >=1.6
Requires-Dist: python-docx-replace
Provides-Extra: alt
Requires-Dist: altair >=5.0 ; extra == 'alt'
Requires-Dist: vl-convert-python >1.3 ; extra == 'alt'
Provides-Extra: dev
Requires-Dist: mypy ; extra == 'dev'
Requires-Dist: ruff ==0.3.4 ; extra == 'dev'
Provides-Extra: doc
Requires-Dist: sphinx ; extra == 'doc'
Requires-Dist: myst-parser ; extra == 'doc'
Requires-Dist: nbsphinx ; extra == 'doc'
Requires-Dist: pydata-sphinx-theme ; extra == 'doc'
Requires-Dist: sphinx-autodoc-typehints >=1.18.3 ; extra == 'doc'
Requires-Dist: sphinx-gallery ; extra == 'doc'
Provides-Extra: test
Requires-Dist: pytest >=7.1 ; extra == 'test'
Requires-Dist: pytest-cov >=3.0.0 ; extra == 'test'
